{"techName":"OpenResty","totalCompaniesNumber":8187,"usingCompaniesNumber":88,"usingCompanies":[{"code":"SSKN","nameJa":null,"nameEn":"STRATA Skin Sciences, Inc."},{"code":"SECOY","nameJa":null,"nameEn":"Secoo Holding Ltd"},{"code":"SRG-PA","nameJa":null,"nameEn":"Seritage Growth Properties"},{"code":"SRG","nameJa":null,"nameEn":"Seritage Growth Properties"},{"code":"SOHU","nameJa":null,"nameEn":"Sohu.com Ltd"},{"code":"SWIN","nameJa":null,"nameEn":"Solowin Holdings, Ltd."},{"code":"SDSTW","nameJa":null,"nameEn":"Stardust Power Inc."},{"code":"SDST","nameJa":null,"nameEn":"Stardust Power Inc."}],"otherInitials":["0","a","b","c","e","f","g","h","i","k","l","m","o","p","q","r","s","t","u","v","w","x","y"]}
